referrers/__init__.py
referrers/impl.py
referrers/networkx-license
referrers/networkx_copy.py
referrers-0.16.1.dist-info/METADATA
referrers-0.16.1.dist-info/WHEEL
referrers-0.16.1.dist-info/licenses/LICENSE
referrers-0.16.1.dist-info/RECORD
