Metadata-Version: 2.4
Name: referrers
Version: 0.16.1
Summary: Finds the graph of referrers for a Python object
License: Apache-2.0
License-File: LICENSE
Author: Neil Ferguson
Requires-Python: >=3.9
Classifier: License :: OSI Approved :: Apache Software License
Classifier: Programming Language :: Python :: 3
Classifier: Programming Language :: Python :: 3.9
Classifier: Programming Language :: Python :: 3.10
Classifier: Programming Language :: Python :: 3.11
Classifier: Programming Language :: Python :: 3.12
Classifier: Programming Language :: Python :: 3.13
Classifier: Programming Language :: Python :: 3.14
Requires-Dist: networkx (>=2.4)
Project-URL: Repository, https://github.com/nfergu/referrers
